num2persian/__init__.py
num2persian/cli.py
num2persian/convert.py
num2persian-2.0.2.dist-info/licenses/LICENSE
num2persian-2.0.2.dist-info/METADATA
num2persian-2.0.2.dist-info/WHEEL
num2persian-2.0.2.dist-info/entry_points.txt
num2persian-2.0.2.dist-info/top_level.txt
num2persian-2.0.2.dist-info/zip-safe
num2persian-2.0.2.dist-info/RECORD
