Metadata-Version: 2.4
Name: num2persian
Version: 2.0.2
Summary: Convert numbers to Persian words
Author-email: Ramin Saljoughinejad <ramin.saljoughi@icloud.com>, Hamed Zeidabadi <zeidabadi73@gmail.com>
Maintainer-email: Ramin Saljoughinejad <ramin.saljoughi@icloud.com>, Hamed Zeidabadi <zeidabadi73@gmail.com>
License: MIT
Project-URL: Homepage, https://github.com/yourusername/num2persian
Project-URL: Repository, https://github.com/yourusername/num2persian
Project-URL: Issues, https://github.com/yourusername/num2persian/issues
Project-URL: Changelog, https://github.com/yourusername/num2persian/blob/main/CHANGELOG.md
Project-URL: NPM Package, https://www.npmjs.com/package/persian-number-words
Keywords: persian,numbers,words,converter,farsi,typescript,multi-language
Classifier: Development Status :: 4 - Beta
Classifier: Intended Audience :: Developers
Classifier: License :: OSI Approved :: MIT License
Classifier: Operating System :: OS Independent
Classifier: Programming Language :: Python :: 3
Classifier: Programming Language :: Python :: 3.8
Classifier: Programming Language :: Python :: 3.9
Classifier: Programming Language :: Python :: 3.10
Classifier: Programming Language :: Python :: 3.11
Classifier: Programming Language :: Python :: 3.12
Classifier: Topic :: Utilities
Classifier: Topic :: Text Processing :: Linguistic
Requires-Python: >=3.8
License-File: LICENSE
Dynamic: license-file
